{
	"saved_hash": "60b1f9d96dd04cef2a84850a838a91a760448ada",
	"files": [
		{
			"key": "c++/v1/__debug_utils/strict_weak_ordering_check.h",
			"value": {
				"items": [
					{
						"k": 501,
						"d": false,
						"iv": false,
						"is": false,
						"n": "_LIBCPP___LIBCXX_DEBUG_STRICT_WEAK_ORDERING_CHECK",
						"t": "",
						"i": "_LIBCPP___LIBCXX_DEBUG_STRICT_WEAK_ORDERING_CHECK",
						"r": "_LIBCPP___LIBCXX_DEBUG_STRICT_WEAK_ORDERING_CHECK",
						"s": "",
						"u": "_LIBCPP___LIBCXX_DEBUG_STRICT_WEAK_ORDERING_CHECK",
						"q": "",
						"w": "",
						"y": "",
						"da": [

						],
						"sf": [
							{
								"items": [

								],
								"h": "75b1d0895eab621f647997787a96559945dcbcb3"
							}
						]
					},
					{
						"k": 30,
						"d": true,
						"iv": false,
						"is": false,
						"n": "__check_strict_weak_ordering_sorted",
						"t": "void (_RandomAccessIterator, _RandomAccessIterator, _Comp &)",
						"i": "std::__1::",
						"r": "template <class _RandomAccessIterator, class _Comp> __attribute__((exclude_from_explicit_instantiation)) __attribute__((abi_tag(\"ne180100\"))) constexpr void __check_strict_weak_ordering_sorted(_RandomAccessIterator __first, _RandomAccessIterator __last, _Comp& __comp)",
						"s": "std::__1",
						"u": "__CHECK_STRICT_WEAK_ORDERING_SORTED",
						"q": "",
						"w": "",
						"y": "",
						"da": [

						],
						"sf": [
							{
								"items": [

								],
								"h": "15d2695e6066b3cbf528583d3ede664bec4b3896"
							}
						]
					}
				]
			}
		},
		{
			"key": "c++/v1/__debug_utils/randomize_range.h",
			"value": {
				"items": [
					{
						"k": 501,
						"d": false,
						"iv": false,
						"is": false,
						"n": "_LIBCPP___LIBCXX_DEBUG_RANDOMIZE_RANGE_H",
						"t": "",
						"i": "_LIBCPP___LIBCXX_DEBUG_RANDOMIZE_RANGE_H",
						"r": "_LIBCPP___LIBCXX_DEBUG_RANDOMIZE_RANGE_H",
						"s": "",
						"u": "_LIBCPP___LIBCXX_DEBUG_RANDOMIZE_RANGE_H",
						"q": "",
						"w": "",
						"y": "",
						"da": [

						],
						"sf": [
							{
								"items": [

								],
								"h": "fccd7d66d821d514debff1254ef0273f1b69b270"
							}
						]
					},
					{
						"k": 30,
						"d": true,
						"iv": false,
						"is": false,
						"n": "__debug_randomize_range",
						"t": "void (_Iterator, _Sentinel)",
						"i": "std::__1::",
						"r": "template <class _AlgPolicy, class _Iterator, class _Sentinel> __attribute__((exclude_from_explicit_instantiation)) __attribute__((abi_tag(\"ne180100\"))) constexpr void __debug_randomize_range(_Iterator __first, _Sentinel __last)",
						"s": "std::__1",
						"u": "__DEBUG_RANDOMIZE_RANGE",
						"q": "",
						"w": "",
						"y": "",
						"da": [

						],
						"sf": [
							{
								"items": [

								],
								"h": "31b4af937b896151fa873a140fef208c8077183b"
							}
						]
					}
				]
			}
		}
	]
}